pulumi_github/__init__.py
pulumi_github/_inputs.py
pulumi_github/_utilities.py
pulumi_github/actions_environment_secret.py
pulumi_github/actions_environment_variable.py
pulumi_github/actions_organization_oidc_subject_claim_customization_template.py
pulumi_github/actions_organization_permissions.py
pulumi_github/actions_organization_secret.py
pulumi_github/actions_organization_secret_repositories.py
pulumi_github/actions_organization_secret_repository.py
pulumi_github/actions_organization_variable.py
pulumi_github/actions_repository_access_level.py
pulumi_github/actions_repository_oidc_subject_claim_customization_template.py
pulumi_github/actions_repository_permissions.py
pulumi_github/actions_runner_group.py
pulumi_github/actions_secret.py
pulumi_github/actions_variable.py
pulumi_github/app_installation_repositories.py
pulumi_github/app_installation_repository.py
pulumi_github/branch.py
pulumi_github/branch_default.py
pulumi_github/branch_protection.py
pulumi_github/branch_protection_v3.py
pulumi_github/codespaces_organization_secret.py
pulumi_github/codespaces_organization_secret_repositories.py
pulumi_github/codespaces_secret.py
pulumi_github/codespaces_user_secret.py
pulumi_github/dependabot_organization_secret.py
pulumi_github/dependabot_organization_secret_repositories.py
pulumi_github/dependabot_secret.py
pulumi_github/emu_group_mapping.py
pulumi_github/enterprise_actions_permissions.py
pulumi_github/enterprise_actions_runner_group.py
pulumi_github/enterprise_organization.py
pulumi_github/get_actions_environment_public_key.py
pulumi_github/get_actions_environment_secrets.py
pulumi_github/get_actions_environment_variables.py
pulumi_github/get_actions_organization_oidc_subject_claim_customization_template.py
pulumi_github/get_actions_organization_public_key.py
pulumi_github/get_actions_organization_registration_token.py
pulumi_github/get_actions_organization_secrets.py
pulumi_github/get_actions_organization_variables.py
pulumi_github/get_actions_public_key.py
pulumi_github-6.9.1.dist-info/METADATA
pulumi_github-6.9.1.dist-info/WHEEL
pulumi_github-6.9.1.dist-info/top_level.txt
pulumi_github-6.9.1.dist-info/RECORD
